miqro/__init__.py
miqro/ha_sensors.py
miqro-1.2.3.dist-info/METADATA
miqro-1.2.3.dist-info/WHEEL
miqro-1.2.3.dist-info/licenses/LICENSE
miqro-1.2.3.dist-info/RECORD
