Metadata-Version: 2.4
Name: miqro
Version: 1.2.3
Summary: MIQRO is an MQTT Micro-Service Library for Python
License-File: LICENSE
Author: Daniel Fett
Author-email: mail@danielfett.de
Requires-Python: >=3.6,<4.0
Classifier: Programming Language :: Python :: 3
Classifier: Programming Language :: Python :: 3.6
Classifier: Programming Language :: Python :: 3.7
Classifier: Programming Language :: Python :: 3.8
Classifier: Programming Language :: Python :: 3.9
Classifier: Programming Language :: Python :: 3.10
Classifier: Programming Language :: Python :: 3.11
Classifier: Programming Language :: Python :: 3.12
Classifier: Programming Language :: Python :: 3.13
Classifier: Programming Language :: Python :: 3.14
Requires-Dist: PyYAML (>=6.0,<7.0)
Requires-Dist: paho-mqtt (>=1.6.1,<2.0.0)
